[{"business_status": "OPERATIONAL", "formatted_address": "Acamapichtli 17, Zona Urbana Ejidal los Reyes Culhuacan, Iztapalapa, 09840 Ciudad de M\u00e9xico, CDMX", "geometry": {"location": {"lat": 19.3470575, "lng": -99.10361669999999}, "viewport": {"northeast": {"lat": 19.34838217989272, "lng": -99.1022741201073}, "southwest": {"lat": 19.34568252010728, "lng": -99.10497377989273}}}, "icon": "https://maps.gstatic.com/mapfiles/place_api/icons/v1/png_71/restaurant-71.png", "name": "PANADER\u00cdA LUPITA", "opening_hours": {"open_now": true}, "place_id": "ChIJcaD-Lgf-0YURV0lGQXvGFEU", "plus_code": {"compound_code": "8VWW+RH Mexico City", "global_code": "76F28VWW+RH"}, "rating": 3.9, "reference": "ChIJcaD-Lgf-0YURV0lGQXvGFEU", "types": ["bakery", "food", "point_of_interest", "store", "establishment"], "user_ratings_total": 28}, {"business_status": "OPERATIONAL", "formatted_address": "Av Estrella No 95, Ricardo Flores Mag\u00f3n, Iztapalapa, 09820 Ciudad de M\u00e9xico, CDMX", "geometry": {"location": {"lat": 19.3520815, "lng": -99.0979131}, "viewport": {"northeast": {"lat": 19.35341952989272, "lng": -99.09658142010728}, "southwest": {"lat": 19.35071987010728, "lng": -99.09928107989273}}}, "icon": "https://maps.gstatic.com/mapfiles/place_api/icons/v1/png_71/restaurant-71.png", "name": "Panader\u00eda Av estrella", "opening_hours": {"open_now": true}, "place_id": "ChIJiZwm0Pz90YURWFUozpvzp08", "plus_code": {"compound_code": "9W22+RR Mexico City", "global_code": "76F29W22+RR"}, "rating": 2.8, "reference": "ChIJiZwm0Pz90YURWFUozpvzp08", "types": ["bakery", "food", "point_of_interest", "store", "establishment"], "user_ratings_total": 6}, {"business_status": "OPERATIONAL", "formatted_address": "Xochiquetzal 92, Estrella del Sur, Iztapalapa, 09820 Ciudad de M\u00e9xico, CDMX", "geometry": {"location": {"lat": 19.3484265, "lng": -99.10003929999999}, "viewport": {"northeast": {"lat": 19.34979262989272, "lng": -99.09873847010728}, "southwest": {"lat": 19.34709297010728, "lng": -99.10143812989273}}}, "icon": "https://maps.gstatic.com/mapfiles/place_api/icons/v1/png_71/restaurant-71.png", "name": "Panaderia Jazmyn", "opening_hours": {"open_now": true}, "place_id": "ChIJ88e7lf390YURII3DjWNJbXQ", "plus_code": {"compound_code": "8VXX+9X Mexico City", "global_code": "76F28VXX+9X"}, "rating": 5, "reference": "ChIJ88e7lf390YURII3DjWNJbXQ", "types": ["bakery", "food", "point_of_interest", "store", "establishment"], "user_ratings_total": 1}, {"business_status": "OPERATIONAL", "formatted_address": "Av, Ermita Iztapalapa 190, Ricardo Flores Mag\u00f3n, Iztapalapa, 09200 CDMX", "geometry": {"location": {"lat": 19.3557008, "lng": -99.098323}, "viewport": {"northeast": {"lat": 19.35693757989272, "lng": -99.09697317010726}, "southwest": {"lat": 19.35423792010728, "lng": -99.09967282989271}}}, "icon": "https://maps.gstatic.com/mapfiles/place_api/icons/v1/png_71/restaurant-71.png", "name": "El Globo Iztapalapa", "opening_hours": {"open_now": true}, "photos": [{"height": 2988, "html_attributions": ["<a href=\"https://maps.google.com/maps/contrib/103192964286047952723\">Herbert Maldonado</a>"], "photo_reference": "CmRaAAAAMUsSONjOXyTcRe3_yKcSI8bix0rXgzHOFBJNkps93xzHE95ZFpJzY5zSCiI6hHPY5t1-YJdNf7WG8VzvDJ4Cua0A3CT5NQ7OWoC23mvcFj2OsW-NjoSHNAOMstgidZFGEhDg7POU_nhKcIbEBisDE9cKGhS3G64nzcJ0HFN2JiFUgTfrn1hyXw", "width": 5312}], "place_id": "ChIJfxo4Czf-0YUR-FiKlxOyF6o", "plus_code": {"compound_code": "9W42+7M Ricardo Flores Mag\u00f3n, Mexico City", "global_code": "76F29W42+7M"}, "price_level": 2, "rating": 4.1, "reference": "ChIJfxo4Czf-0YUR-FiKlxOyF6o", "types": ["bakery", "cafe", "food", "point_of_interest", "store", "establishment"], "user_ratings_total": 1505}, {"business_status": "OPERATIONAL", "formatted_address": "Puentetitla 26, Amp Ricardo Flores Mag\u00f3n, Iztapalapa, 09820 Ciudad de M\u00e9xico, CDMX", "geometry": {"location": {"lat": 19.354373, "lng": -99.09895759999999}, "viewport": {"northeast": {"lat": 19.35573212989273, "lng": -99.09763237010729}, "southwest": {"lat": 19.35303247010728, "lng": -99.10033202989273}}}, "icon": "https://maps.gstatic.com/mapfiles/place_api/icons/v1/png_71/restaurant-71.png", "name": "Popoca Panader\u00eda Puente Titla", "opening_hours": {"open_now": true}, "place_id": "ChIJU6DI5uL90YURow69k0vqxHk", "plus_code": {"compound_code": "9W32+PC Mexico City", "global_code": "76F29W32+PC"}, "rating": 4, "reference": "ChIJU6DI5uL90YURow69k0vqxHk", "types": ["bakery", "food", "point_of_interest", "store", "establishment"], "user_ratings_total": 9}, {"business_status": "OPERATIONAL", "formatted_address": "Puente Titla 27, Iztapalapa, 09829 Ciudad de M\u00e9xico, CDMX", "geometry": {"location": {"lat": 19.3505928, "lng": -99.0954232}, "viewport": {"northeast": {"lat": 19.35192037989272, "lng": -99.0941056701073}, "southwest": {"lat": 19.34922072010728, "lng": -99.09680532989273}}}, "icon": "https://maps.gstatic.com/mapfiles/place_api/icons/v1/png_71/restaurant-71.png", "name": "Panaderia", "opening_hours": {"open_now": true}, "place_id": "ChIJe79Ne_v90YUR7NdD6tfHfLw", "plus_code": {"compound_code": "9W23+6R Mexico City", "global_code": "76F29W23+6R"}, "rating": 3.7, "reference": "ChIJe79Ne_v90YUR7NdD6tfHfLw", "types": ["bakery", "food", "point_of_interest", "store", "establishment"], "user_ratings_total": 10}, {"business_status": "OPERATIONAL", "formatted_address": "MZ 41, Lote 9, Calle Tlatolcatzin, Zona Urbana Ejidal Los Reyes Culhuacan, Iztapalapa, 09840 Ciudad de M\u00e9xico, CDMX", "geometry": {"location": {"lat": 19.3447514, "lng": -99.1003207}, "viewport": {"northeast": {"lat": 19.34610352989272, "lng": -99.09898077010727}, "southwest": {"lat": 19.34340387010727, "lng": -99.10168042989272}}}, "icon": "https://maps.gstatic.com/mapfiles/place_api/icons/v1/png_71/restaurant-71.png", "name": "PANADER\u00cdA", "opening_hours": {"open_now": true}, "place_id": "ChIJ_2_gO_790YURTBgXm4vJg4A", "plus_code": {"compound_code": "8VVX+WV Mexico City", "global_code": "76F28VVX+WV"}, "rating": 5, "reference": "ChIJ_2_gO_790YURTBgXm4vJg4A", "types": ["bakery", "food", "point_of_interest", "store", "establishment"], "user_ratings_total": 3}, {"business_status": "OPERATIONAL", "formatted_address": "Av. Toltecas 3, Sta B\u00e1rbara, Iztapalapa, 09000 Ciudad de M\u00e9xico, CDMX", "geometry": {"location": {"lat": 19.356327, "lng": -99.10548159999999}, "viewport": {"northeast": {"lat": 19.35769717989272, "lng": -99.10419077010727}, "southwest": {"lat": 19.35499752010728, "lng": -99.10689042989272}}}, "icon": "https://maps.gstatic.com/mapfiles/place_api/icons/v1/png_71/restaurant-71.png", "name": "Pasteler\u00edas Esperanza (Toltecas)", "opening_hours": {"open_now": true}, "photos": [{"height": 2448, "html_attributions": ["<a href=\"https://maps.google.com/maps/contrib/118190373359441140712\">A Google User</a>"], "photo_reference": "CmRaAAAAGnVP8n8Q_SMSomfL9SY_QDuQNqlTYQ_bTQWfxOWFkgw1j0VVSY7BrUVhrnyvpr-xhGSLhqPIvu06k2WlQBneVwcMQVNROY4ZHBRdjfEZkS7KFTz1Ridz9f6CE--KIyQwEhAOLouIuSlx8XnePnXLJ7DrGhQhIYxMxXtyYzfzNhh1iD7944IZ3w", "width": 3264}], "place_id": "ChIJfyoDtQv-0YUR54XOev39Ky4", "plus_code": {"compound_code": "9V4V+GR Mexico City", "global_code": "76F29V4V+GR"}, "price_level": 2, "rating": 4.2, "reference": "ChIJfyoDtQv-0YUR54XOev39Ky4", "types": ["bakery", "food", "point_of_interest", "store", "establishment"], "user_ratings_total": 389}, {"business_status": "OPERATIONAL", "formatted_address": "Convento 33, El Santuario, Iztapalapa, 09820 Ciudad de M\u00e9xico, CDMX", "geometry": {"location": {"lat": 19.3540645, "lng": -99.0948098}, "viewport": {"northeast": {"lat": 19.35540272989272, "lng": -99.09349887010728}, "southwest": {"lat": 19.35270307010728, "lng": -99.09619852989272}}}, "icon": "https://maps.gstatic.com/mapfiles/place_api/icons/v1/png_71/restaurant-71.png", "name": "Panaderia Popoca", "opening_hours": {"open_now": true}, "place_id": "ChIJs_9CvOT90YURIEsAjNtGkps", "plus_code": {"compound_code": "9W34+J3 Mexico City", "global_code": "76F29W34+J3"}, "rating": 4, "reference": "ChIJs_9CvOT90YURIEsAjNtGkps", "types": ["bakery", "food", "point_of_interest", "store", "establishment"], "user_ratings_total": 2}, {"business_status": "OPERATIONAL", "formatted_address": "Andador 13 de Toltecas 67, Sta B\u00e1rbara, Iztapalapa, 09000 Ciudad de M\u00e9xico, CDMX", "geometry": {"location": {"lat": 19.3581164, "lng": -99.10484939999999}, "viewport": {"northeast": {"lat": 19.35947577989273, "lng": -99.1035272201073}, "southwest": {"lat": 19.35677612010728, "lng": -99.10622687989273}}}, "icon": "https://maps.gstatic.com/mapfiles/place_api/icons/v1/png_71/restaurant-71.png", "name": "Panader\u00eda Mary", "opening_hours": {"open_now": true}, "photos": [{"height": 5312, "html_attributions": ["<a href=\"https://maps.google.com/maps/contrib/115841498968743580968\">A Google User</a>"], "photo_reference": "CmRZAAAAHeLo8Iyeq8w59iUuLUrGYNm2rl9pAH841eEZ5ve2lCBcugAXPu-E0r_KGhY6yPjeNgFtRVweMHXq_tq58m4u11nUUPPSGibFrPztsG_JvmVztZ9K46ahGAb3nfUcRVUhEhD6Cz7oODQGWIVVTlq9ObArGhR1SLG3KBnhu2CnE4cESxHOCjt6Nw", "width": 2992}], "place_id": "ChIJFfrnYgn-0YUR-VrrYdqLikg", "plus_code": {"compound_code": "9V5W+63 Mexico City", "global_code": "76F29V5W+63"}, "rating": 3.4, "reference": "ChIJFfrnYgn-0YUR-VrrYdqLikg", "types": ["bakery", "food", "point_of_interest", "store", "establishment"], "user_ratings_total": 5}, {"business_status": "OPERATIONAL", "formatted_address": "Calle Cuauht\u00e9moc 15, Los Reyes Culhuacan, Iztapalapa, 08900 Ciudad de M\u00e9xico, CDMX", "geometry": {"location": {"lat": 19.3448866, "lng": -99.1098044}, "viewport": {"northeast": {"lat": 19.34622527989272, "lng": -99.10845307010727}, "southwest": {"lat": 19.34352562010728, "lng": -99.11115272989271}}}, "icon": "https://maps.gstatic.com/mapfiles/place_api/icons/v1/png_71/restaurant-71.png", "name": "Panader\u00eda La Providencia", "opening_hours": {"open_now": true}, "photos": [{"height": 2736, "html_attributions": ["<a href=\"https://maps.google.com/maps/contrib/101074682067668841765\">MiGuel MGL</a>"], "photo_reference": "CmRaAAAArLSz4MTxWCGgAi6G57xXObW_kTsfwqykibX9qR-ToiRq3pvmvfjbtu4odkN58_57TTcchhuquTIQ9_vrQ74PamShUsXWA-IcBhXfADeiREs3qAclYndJOjhKRAlDFKQ3EhDQMHruGM4bx6F4UnYkw6NBGhSc-y-UVLrBbBV5434PbNCFBsdN7g", "width": 3648}], "place_id": "ChIJEfYOdQP-0YURYYfSXXIcSpo", "plus_code": {"compound_code": "8VVR+X3 Mexico City", "global_code": "76F28VVR+X3"}, "rating": 4.1, "reference": "ChIJEfYOdQP-0YURYYfSXXIcSpo", "types": ["bakery", "food", "point_of_interest", "store", "establishment"], "user_ratings_total": 33}, {"business_status": "OPERATIONAL", "formatted_address": "5 de Mayo 71, San Ignacio, Iztapalapa, 09000 Ciudad de M\u00e9xico, CDMX", "geometry": {"location": {"lat": 19.3617412, "lng": -99.0954093}, "viewport": {"northeast": {"lat": 19.36305367989272, "lng": -99.09407137010729}, "southwest": {"lat": 19.36035402010728, "lng": -99.09677102989274}}}, "icon": "https://maps.gstatic.com/mapfiles/place_api/icons/v1/png_71/restaurant-71.png", "name": "PANIFICADORA EL PROGRESO", "opening_hours": {"open_now": true}, "photos": [{"height": 677, "html_attributions": ["<a href=\"https://maps.google.com/maps/contrib/102400113048090446776\">IOREKBS ALBERTO TORRES</a>"], "photo_reference": "CmRaAAAAjzWlm0li0nkoZiGyFJR2vJnRTpbidSr6kbVUWVt0gl9TbngFLhTequRl0W9za9jtd47DKj6a_rOu7KZbVnOdKA3yXSqDJ8NiSQwkiZvfv72ICebGQaFTUEjK2rDFntguEhDkBLnYGn-5XtiN4fyImjtGGhQyVc68grSSUNLjeP4DH2EaaCkqFg", "width": 960}], "place_id": "ChIJW6DsKef90YUR8_2dIbnBAaw", "plus_code": {"compound_code": "9W63+MR Mexico City", "global_code": "76F29W63+MR"}, "price_level": 1, "rating": 4.2, "reference": "ChIJW6DsKef90YUR8_2dIbnBAaw", "types": ["bakery", "food", "point_of_interest", "store", "establishment"], "user_ratings_total": 175}, {"business_status": "OPERATIONAL", "formatted_address": "Campesinos 289, Progreso del Sur, Iztapalapa, 09810 Ciudad de M\u00e9xico, CDMX", "geometry": {"location": {"lat": 19.3528644, "lng": -99.11130089999999}, "viewport": {"northeast": {"lat": 19.35429752989272, "lng": -99.10994097010727}, "southwest": {"lat": 19.35159787010728, "lng": -99.11264062989272}}}, "icon": "https://maps.gstatic.com/mapfiles/place_api/icons/v1/png_71/restaurant-71.png", "name": "Panader\u00eda y Pasteler\u00eda Progreso Del Sur", "opening_hours": {"open_now": true}, "photos": [{"height": 4608, "html_attributions": ["<a href=\"https://maps.google.com/maps/contrib/101226785813533469313\">A Google User</a>"], "photo_reference": "CmRaAAAAFJv3eQQKrROZlWOs_421horUBQXu3ILmWElBAmfX_1AEbbeeauC-WKal7mEk0a6ZSS45JEkfmf6YGub8e47wL3bVJguanTkrFSgIaA9-bOfiS6WmqBZc_bYmeT3ToPbWEhCNfXb91hgdYDB8TnKFBV-SGhQIIiEwnepl37zdLrAQJ5EDjdnHMg", "width": 3456}], "place_id": "ChIJN9uS7Q_-0YURSYTVa7BBzOQ", "plus_code": {"compound_code": "9V3Q+4F Mexico City", "global_code": "76F29V3Q+4F"}, "rating": 4.3, "reference": "ChIJN9uS7Q_-0YURSYTVa7BBzOQ", "types": ["bakery", "food", "point_of_interest", "store", "establishment"], "user_ratings_total": 10}, {"business_status": "OPERATIONAL", "formatted_address": "1a Cuauht\u00e9moc Mz15 Lt16, Los Reyes Culhuacan, Iztapalapa, 09840 Ciudad de M\u00e9xico, CDMX", "geometry": {"location": {"lat": 19.3457576, "lng": -99.1044141}, "viewport": {"northeast": {"lat": 19.34712812989272, "lng": -99.10305842010727}, "southwest": {"lat": 19.34442847010728, "lng": -99.10575807989272}}}, "icon": "https://maps.gstatic.com/mapfiles/place_api/icons/v1/png_71/restaurant-71.png", "name": "PAN-CHO Traditional Bakery", "opening_hours": {"open_now": false}, "photos": [{"height": 3456, "html_attributions": ["<a href=\"https://maps.google.com/maps/contrib/110655542914957886842\">Zyanya S\u00e1nchez Mota</a>"], "photo_reference": "CmRaAAAAFbliZjKUj3mjnKouWY7HKxYLFHxnoUxpwkOk6-zYV9wtlY3zzs9Lw_WH0b2SW33T5vVAHSKinpb6YGIeIWhTaSZDGWf9Ooamobk3BIaLemeKbHf0AFDXuBPH0HZK776OEhBRf3WTjagbrmmPSUZPeCMLGhT5jz2hgLJCVJBVAr03PQDXkk-sYg", "width": 4608}], "place_id": "ChIJM3l1KAH-0YURD30_eIPmnlw", "plus_code": {"compound_code": "8VWW+86 Los Reyes Culhuacan, Mexico City", "global_code": "76F28VWW+86"}, "price_level": 2, "rating": 4.5, "reference": "ChIJM3l1KAH-0YURD30_eIPmnlw", "types": ["bakery", "cafe", "food", "point_of_interest", "store", "establishment"], "user_ratings_total": 149}, {"business_status": "OPERATIONAL", "formatted_address": "Gral. Anaya 133, Sta B\u00e1rbara, Iztapalapa, 09000 Ciudad de M\u00e9xico, CDMX", "geometry": {"location": {"lat": 19.358531, "lng": -99.10103199999999}, "viewport": {"northeast": {"lat": 19.35989362989272, "lng": -99.0997124201073}, "southwest": {"lat": 19.35719397010728, "lng": -99.10241207989273}}}, "icon": "https://maps.gstatic.com/mapfiles/place_api/icons/v1/png_71/restaurant-71.png", "name": "Panader\u00eda Arroyo Jr", "opening_hours": {"open_now": true}, "place_id": "ChIJR9iKweH90YURzhVXD16d5hw", "plus_code": {"compound_code": "9V5X+CH Mexico City", "global_code": "76F29V5X+CH"}, "rating": 0, "reference": "ChIJR9iKweH90YURzhVXD16d5hw", "types": ["bakery", "food", "point_of_interest", "store", "establishment"], "user_ratings_total": 0}, {"business_status": "OPERATIONAL", "formatted_address": "Cerrada Iturbide 127, San Lucas, Iztapalapa, 09000 Ciudad de M\u00e9xico, CDMX", "geometry": {"location": {"lat": 19.35995, "lng": -99.09670009999999}, "viewport": {"northeast": {"lat": 19.36130882989272, "lng": -99.09538647010729}, "southwest": {"lat": 19.35860917010728, "lng": -99.09808612989274}}}, "icon": "https://maps.gstatic.com/mapfiles/place_api/icons/v1/png_71/restaurant-71.png", "name": "Panader\u00eda La Favorita", "opening_hours": {"open_now": true}, "place_id": "ChIJ7wUeR-H90YURZWPrfspVs98", "plus_code": {"compound_code": "9W53+X8 San Lucas, Mexico City", "global_code": "76F29W53+X8"}, "rating": 4.2, "reference": "ChIJ7wUeR-H90YURZWPrfspVs98", "types": ["bakery", "food", "point_of_interest", "store", "establishment"], "user_ratings_total": 5}, {"business_status": "OPERATIONAL", "formatted_address": "Ermita Iztapalapa 10, Sta B\u00e1rbara, Iztapalapa, 09000 Ciudad de M\u00e9xico, CDMX", "geometry": {"location": {"lat": 19.3560207, "lng": -99.1024338}, "viewport": {"northeast": {"lat": 19.35732127989272, "lng": -99.1010794701073}, "southwest": {"lat": 19.35462162010728, "lng": -99.10377912989273}}}, "icon": "https://maps.gstatic.com/mapfiles/place_api/icons/v1/png_71/restaurant-71.png", "name": "Panader\u00eda y pasteler\u00eda", "opening_hours": {"open_now": false}, "place_id": "ChIJw4XXyAn-0YURCwySbhSu7ww", "plus_code": {"compound_code": "9V4X+C2 Mexico City", "global_code": "76F29V4X+C2"}, "rating": 0, "reference": "ChIJw4XXyAn-0YURCwySbhSu7ww", "types": ["bakery", "food", "point_of_interest", "store", "establishment"], "user_ratings_total": 0}, {"business_status": "OPERATIONAL", "formatted_address": "Camino a Los Reyes 70, Valle de Luces, Iztapalapa, 09800 Ciudad de M\u00e9xico, CDMX", "geometry": {"location": {"lat": 19.3421071, "lng": -99.10603210000001}, "viewport": {"northeast": {"lat": 19.34345232989272, "lng": -99.10466007010729}, "southwest": {"lat": 19.34075267010728, "lng": -99.10735972989274}}}, "icon": "https://maps.gstatic.com/mapfiles/place_api/icons/v1/png_71/restaurant-71.png", "name": "Panaderia San Ricardo", "opening_hours": {"open_now": true}, "place_id": "ChIJKawdkwH-0YURkETui35AUNM", "plus_code": {"compound_code": "8VRV+RH Mexico City", "global_code": "76F28VRV+RH"}, "rating": 5, "reference": "ChIJKawdkwH-0YURkETui35AUNM", "types": ["bakery", "food", "point_of_interest", "store", "establishment"], "user_ratings_total": 1}, {"business_status": "OPERATIONAL", "formatted_address": "Campesinos 279, Colonia, Progreso del Sur, Iztapalapa, 09810 Ciudad de M\u00e9xico, CDMX", "geometry": {"location": {"lat": 19.3530038, "lng": -99.111864}, "viewport": {"northeast": {"lat": 19.35439212989272, "lng": -99.11051072010727}, "southwest": {"lat": 19.35169247010728, "lng": -99.11321037989272}}}, "icon": "https://maps.gstatic.com/mapfiles/place_api/icons/v1/png_71/restaurant-71.png", "name": "Panaderia Artesanal \"Horneado Con Amor\"", "opening_hours": {"open_now": true}, "photos": [{"height": 972, "html_attributions": ["<a href=\"https://maps.google.com/maps/contrib/100049574865860445389\">A Google User</a>"], "photo_reference": "CmRaAAAAoLQSiQaCXv4sNwrUtEZUivmJYEvt1WXec1n8PzQQE2KD-_GfWVRYOHsZy7aWzDrWjqMHjw0Yx-L2tQK7e32cOxYQA0esd-ZKkDo2Iq-Xkrtx_HYDaZtym4IW44Ol3l3YEhC4SuL_wXbOe2TzEaJyVGicGhRSr427iwJIP9gAXbaErI4gZqoqXg", "width": 1044}], "place_id": "ChIJQSvBW2n_0YURAsxs_6f2r5A", "plus_code": {"compound_code": "9V3Q+67 Mexico City", "global_code": "76F29V3Q+67"}, "rating": 5, "reference": "ChIJQSvBW2n_0YURAsxs_6f2r5A", "types": ["bakery", "food", "point_of_interest", "store", "establishment"], "user_ratings_total": 2}, {"business_status": "OPERATIONAL", "formatted_address": "Allende 36, San Jos\u00e9, Iztapalapa, 09000 Ciudad de M\u00e9xico, CDMX", "geometry": {"location": {"lat": 19.3632572, "lng": -99.0892873}, "viewport": {"northeast": {"lat": 19.36458562989272, "lng": -99.08794387010728}, "southwest": {"lat": 19.36188597010728, "lng": -99.09064352989273}}}, "icon": "https://maps.gstatic.com/mapfiles/place_api/icons/v1/png_71/restaurant-71.png", "name": "PANADERIA AZTECA", "opening_hours": {"open_now": true}, "photos": [{"height": 3120, "html_attributions": ["<a href=\"https://maps.google.com/maps/contrib/103486929912373955638\">Ana Nieto Arteaga</a>"], "photo_reference": "CmRaAAAAZV38G2SNiyB2aRd-wQRlcd06NdEVTIyxd_nFkk6WAjmBuqoQQDxJpAoYsgpvcKLovSGqrz_opUeDu6fp4viWqGafZyBUbxCWWvEa_h8FuQQnkgkGve5FrScV1fxmFXFVEhDdBqYAf8_QudftzfDznvnmGhQdt0DuA-Yny74xPKzkreFZv3wtAQ", "width": 4160}], "place_id": "ChIJBVNgbOj90YURCxsWtSVhk64", "plus_code": {"compound_code": "9W76+87 Mexico City", "global_code": "76F29W76+87"}, "rating": 3.8, "reference": "ChIJBVNgbOj90YURCxsWtSVhk64", "types": ["bakery", "food", "point_of_interest", "store", "establishment"], "user_ratings_total": 137}]